brainframe_sys_tools/.python-version
brainframe_sys_tools/__init__.py
brainframe_sys_tools/bf_info.py
brainframe_sys_tools/bf_service_monitor.py
brainframe_sys_tools/bf_ssh_tunnel.py
brainframe_sys_tools/brainframe_monitor/benchmarker.py
brainframe_sys_tools/brainframe_monitor/brainframe_monitor.py
brainframe_sys_tools/brainframe_monitor/curses_utils.py
brainframe_sys_tools/brainframe_monitor/fake_screen.py
brainframe_sys_tools/brainframe_monitor/report.py
brainframe_sys_tools/check_memory.py
brainframe_sys_tools/cli.py
brainframe_sys_tools/command_utils.py
brainframe_sys_tools/perf_monitor.py
brainframe_sys_tools/print_utils.py
brainframe_sys_tools/translations/portal.en.yml
brainframe_sys_tools-0.5.6.dist-info/COPYING
brainframe_sys_tools-0.5.6.dist-info/METADATA
brainframe_sys_tools-0.5.6.dist-info/WHEEL
brainframe_sys_tools-0.5.6.dist-info/entry_points.txt
brainframe_sys_tools-0.5.6.dist-info/RECORD
